pylib_explorer/__init__.py
pylib_explorer/cli.py
pylib_explorer/core.py
pylib_explorer/utils.py
pylib_explorer/llm/__init__.py
pylib_explorer/llm/claude_client.py
pylib_explorer/llm/openai_client.py
tests/__init__.py
tests/test_core.py
pylibexplorer-0.1.1.dist-info/LICENSE
pylibexplorer-0.1.1.dist-info/METADATA
pylibexplorer-0.1.1.dist-info/WHEEL
pylibexplorer-0.1.1.dist-info/entry_points.txt
pylibexplorer-0.1.1.dist-info/top_level.txt
pylibexplorer-0.1.1.dist-info/RECORD
